AUTHORS.rst
LICENSE
README.md
setup.cfg
setup.py
ta_sites/__init__.py
ta_sites.egg-info/PKG-INFO
ta_sites.egg-info/SOURCES.txt
ta_sites.egg-info/dependency_links.txt
ta_sites.egg-info/not-zip-safe
ta_sites.egg-info/requires.txt
ta_sites.egg-info/top_level.txt
ta_sites/always_care/__init__.py
ta_sites/always_care/exceptions.py
ta_sites/always_care/requests_core.py
ta_sites/basic/__init__.py
ta_sites/basic/core.py
ta_sites/basic/exceptions.py
ta_sites/central_reach/__init__.py
ta_sites/central_reach/core.py
ta_sites/central_reach/exceptions.py
ta_sites/central_reach/requests_core.py
ta_sites/quickbooks/__init__.py
ta_sites/quickbooks/core.py
ta_sites/quickbooks/grouped_row.py
ta_sites/salesforce/__init__.py
ta_sites/salesforce/core.py
ta_sites/versant/__init__.py
ta_sites/versant/exceptions.py
ta_sites/versant/requests_core.py