Metadata-Version: 2.4
Name: ta_sites
Version: 0.5.7
Summary: TA Sites
Home-page: https://www.thoughtfulautomation.com/
Author: Serhii Romanets
Author-email: serhii.romanets@thoughtful.ai
Keywords: ta_sites
Classifier: Programming Language :: Python :: 3
Classifier: License :: OSI Approved :: MIT License
Classifier: Operating System :: OS Independent
License-File: LICENSE
License-File: AUTHORS.rst
Requires-Dist: requests
Requires-Dist: datetime
Requires-Dist: retry
Dynamic: author
Dynamic: author-email
Dynamic: classifier
Dynamic: description
Dynamic: description-content-type
Dynamic: home-page
Dynamic: keywords
Dynamic: license-file
Dynamic: requires-dist
Dynamic: summary
